afids_regrf/__init__.py
afids_regrf/apply.py
afids_regrf/notebooks/auto-afids_refactor_dev_compare.ipynb
afids_regrf/notebooks/auto-afids_refactor_dev_test.ipynb
afids_regrf/notebooks/auto-afids_refactor_train.ipynb
afids_regrf/registration/config/config.yml
afids_regrf/registration/resources/c3d_affine_tool
afids_regrf/registration/resources/dataset_description_afids.json
afids_regrf/registration/resources/dataset_description_mni_space.json
afids_regrf/registration/resources/dummy.fcsv
afids_regrf/registration/resources/mni_icbm152_t1_tal_nlin_asym_09c.nii.gz
afids_regrf/registration/workflow/Snakefile
afids_regrf/registration/workflow/envs/mapping.yaml
afids_regrf/registration/workflow/registration_decoupling.py
afids_regrf/registration/workflow/rules/mniTransform.smk
afids_regrf/registration/workflow/rules/mniTransform_withbet.smk
afids_regrf/registration/workflow/scripts/commonsmk/LICENSE
afids_regrf/registration/workflow/scripts/commonsmk/__init__.py
afids_regrf/registration/workflow/scripts/commonsmk/commonsmk.py
afids_regrf/registration/workflow/scripts/commonsmk/setup.py
afids_regrf/registration/workflow/scripts/imresize.py
afids_regrf/registration/workflow/scripts/tform_script.py
afids_regrf/resources/__init__.py
afids_regrf/resources/feature_offsets.npz
afids_regrf/resources/tpl-MNI152NLin2009cAsym_res-01_desc-groundtruth_afids.fcsv
afids_regrf/train.py
afids_regrf/utils.py
afids_regrf-0.3.0.dist-info/LICENSE
afids_regrf-0.3.0.dist-info/METADATA
afids_regrf-0.3.0.dist-info/entry_points.txt
afids_regrf-0.3.0.dist-info/WHEEL
afids_regrf-0.3.0.dist-info/RECORD
