Metadata-Version: 2.1
Name: afids-regrf
Version: 0.3.0
Summary: 
Author: Your Name
Author-email: you@example.com
Requires-Python: >3.8.1,<4
Classifier: Programming Language :: Python :: 3
Classifier: Programming Language :: Python :: 3.9
Classifier: Programming Language :: Python :: 3.10
Classifier: Programming Language :: Python :: 3.11
Requires-Dist: importlib-resources (>=5.12.0,<6.0.0)
Requires-Dist: joblib (>=1.2.0,<2.0.0)
Requires-Dist: nibabel (>=5.0.1,<6.0.0)
Requires-Dist: pandas (>=1.5.3,<2.0.0)
Requires-Dist: scikit-learn (>=1.2.1,<2.0.0)
Requires-Dist: typing-extensions (>=4.6.3,<5.0.0)
